IOPrintStream/__init__.py
IOStream/__init__.py
IOPrintStream-0.0.1.dist-info/LICENSE
IOPrintStream-0.0.1.dist-info/METADATA
IOPrintStream-0.0.1.dist-info/WHEEL
IOPrintStream-0.0.1.dist-info/top_level.txt
IOPrintStream-0.0.1.dist-info/RECORD
